docint/__init__.py
docint/doc.py
docint/errors.py
docint/glossary.txt
docint/hierarchy.py
docint/models/layoutlm/data_gen.py
docint/page.py
docint/pipeline/__init__.py
docint/pipeline/body_marker.py
docint/pipeline/do_nothing.py
docint/pipeline/gcv_recognizer.py
docint/pipeline/html_gen.py
docint/pipeline/infer_layoutlm.py
docint/pipeline/list_finder.py
docint/pipeline/num_marker.py
docint/pipeline/order_builder.py
docint/pipeline/page_orienter.py
docint/pipeline/pdf_reader.py
docint/pipeline/pdftable_finder.py
docint/pipeline/region_differ.py
docint/pipeline/rotation_detector.py
docint/pipeline/table_builder_edges.py
docint/pipeline/table_builder_words.py
docint/pipeline/table_edge_finder.py
docint/pipeline/table_finder.py
docint/pipeline/website_gen.py
docint/pipeline/wordfreq_writer.py
docint/pipeline/words_arranger.py
docint/pipeline/words_fixer.py
docint/region.py
docint/shape.py
docint/span.py
docint/table.py
docint/util.py
docint/vision.py
docint/word.py
docint/word_line.py
docint-0.1.2.dist-info/WHEEL
docint-0.1.2.dist-info/METADATA
docint-0.1.2.dist-info/RECORD
