Metadata-Version: 2.1
Name: docint
Version: 0.1.2
Summary: Extracting information from DOCuments INTelligently.
Home-page: https://github.com/mukundesh/docint
License: MIT
Author: Mukund Deshpande
Author-email: mukundesh@outlook.com
Requires-Python: >=3.7.1,<4.0
Classifier: Development Status :: 2 - Pre-Alpha
Classifier: Intended Audience :: Developers
Classifier: License :: OSI Approved :: MIT License
Classifier: Natural Language :: English
Classifier: Programming Language :: Python :: 3
Classifier: Programming Language :: Python :: 3.10
Classifier: Programming Language :: Python :: 3.7
Classifier: Programming Language :: Python :: 3.8
Classifier: Programming Language :: Python :: 3.9
Provides-Extra: dev
Provides-Extra: doc
Provides-Extra: test
Requires-Dist: PyYAML (>=6.0,<7.0)
Requires-Dist: black (>=22.6.0,<23.0.0); extra == "test"
Requires-Dist: bump2version (>=1.0.1,<2.0.0); extra == "dev"
Requires-Dist: flake8 (>=3.9.2,<4.0.0); extra == "test"
Requires-Dist: flake8-docstrings (>=1.6.0,<2.0.0); extra == "test"
Requires-Dist: google-cloud-storage (>=1.44.0,<2.0.0)
Requires-Dist: google-cloud-vision (>=2.6.3,<3.0.0)
Requires-Dist: isort (>=5.10.1,<6.0.0); extra == "test"
Requires-Dist: jsview (>=1.2,<2.0)
Requires-Dist: mkdocs (>=1.3.0,<2.0.0); extra == "doc"
Requires-Dist: mkdocs-autorefs (>=0.4.1,<0.5.0); extra == "doc"
Requires-Dist: mkdocs-gen-files (>=0.3.5,<0.4.0)
Requires-Dist: mkdocs-include-markdown-plugin (>=3.5.2,<4.0.0); extra == "doc"
Requires-Dist: mkdocs-literate-nav (>=0.4.1,<0.5.0)
Requires-Dist: mkdocs-material (>=8.3.9,<9.0.0); extra == "doc"
Requires-Dist: mkdocs-material-extensions (>=1.0.3,<2.0.0)
Requires-Dist: mkdocs-section-index (>=0.3.4,<0.4.0)
Requires-Dist: mkdocstrings[python] (>=0.19.0,<0.20.0); extra == "doc"
Requires-Dist: more-itertools (>=8.12.0,<9.0.0)
Requires-Dist: msgpack (>=1.0.3,<2.0.0)
Requires-Dist: numpy (<1.22.0)
Requires-Dist: opencv-python (>=4.4.0.46,<5.0.0.0)
Requires-Dist: pdf2image (>=1.16.0,<2.0.0)
Requires-Dist: pdfplumber (>=0.6.0,<0.7.0)
Requires-Dist: pip (>=22.1.2,<23.0.0); extra == "dev"
Requires-Dist: pipdeptree (>=2.2.1,<3.0.0)
Requires-Dist: polyleven (>=0.7,<0.8)
Requires-Dist: pydantic (==1.9.0)
Requires-Dist: pyenchant (>=3.2.2,<4.0.0)
Requires-Dist: pytest (>=7.1.2,<8.0.0); extra == "test"
Requires-Dist: pytest-cov (>=3.0.0,<4.0.0); extra == "test"
Requires-Dist: python-dateutil (>=2.8.2,<3.0.0)
Requires-Dist: rich (>=12.5.1,<13.0.0)
Requires-Dist: tox (>=3.25.1,<4.0.0); extra == "dev"
Requires-Dist: transformers[torch] (>=4.20.1,<5.0.0)
Requires-Dist: twine (>=4.0.1,<5.0.0); extra == "dev"
